trajallocpy/ACBBA copy.py
trajallocpy/ACBBA.py
trajallocpy/Agent.py
trajallocpy/CBBA.py
trajallocpy/CoverageProblem.py
trajallocpy/Experiment.py
trajallocpy/Task.py
trajallocpy/TaskGenerator.py
trajallocpy/Utility.py
trajallocpy/VisibilityGraph.py
trajallocpy/__init__.py
trajallocpy-0.0.13.dist-info/LICENCE
trajallocpy-0.0.13.dist-info/METADATA
trajallocpy-0.0.13.dist-info/WHEEL
trajallocpy-0.0.13.dist-info/top_level.txt
trajallocpy-0.0.13.dist-info/RECORD
