Metadata-Version: 2.1
Name: trajallocpy
Version: 0.0.13
Summary: TrajAllocPy is a Python library that provides functionality for trajectory task Allocaition using Consensus based bundle algorithm
Home-page: 
Author: Kasper Rømer Grøntved
Author-email: Kasper Rømer Grøntved <kaspergrontved@gmail.com>
Classifier: Development Status :: 4 - Beta
Classifier: License :: OSI Approved :: MIT License
Classifier: Programming Language :: Python :: 3.10
Classifier: Programming Language :: Python :: 3.11
Requires-Python: >=3.10
License-File: LICENCE
Provides-Extra: test
Requires-Dist: pytest; extra == "test"
